hundo/Snakefile
hundo/__init__.py
hundo/blast.py
hundo/crest_classifier.py
hundo/environment.yml
hundo/fasta.py
hundo/hundo.py
hundo/unite_classifier.py
hundo/scripts/build_report.py
hundo-1.2.8.dist-info/LICENSE.txt
hundo-1.2.8.dist-info/METADATA
hundo-1.2.8.dist-info/WHEEL
hundo-1.2.8.dist-info/entry_points.txt
hundo-1.2.8.dist-info/top_level.txt
hundo-1.2.8.dist-info/RECORD
