Metadata-Version: 2.1
Name: hundo
Version: 1.2.8
Summary: Amplicon processing protocol
Home-page: https://github.com/pnnl/hundo
Author: Joe Brown
Author-email: joe.brown@pnnl.gov
License: MIT
Platform: UNKNOWN
